{"subsection_name": null, "pub_date": "2011-10-25T12:26:11Z", "byline": {"original": "By THE NEW YORK TIMES", "organization": "THE NEW YORK TIMES", "person": []}, "abstract": "Middle-class families are struggling to pay for long-term care.", "word_count": 368, "print_page": null, "news_desk": null, "snippet": "Middle-class families are struggling to pay for long-term care.", "multimedia": [], "source": "The New York Times", "blog": [], "keywords": [{"name": "type_of_material", "value": "News", "rank": "1"}, {"name": "subject", "value": "Elderly", "rank": "3"}, {"name": "subject", "value": "Elder Care", "rank": "2"}], "type_of_material": "Blog", "lead_paragraph": "The apparent demise of the Class Act leaves many middle-income Americans struggling to cope with rising expenses for long-term care for family members, The Times reported on Tuesday.", "web_url": "http://newoldage.blogs.nytimes.com/2011/10/25/the-crisis-in-long-term-care/", "section_name": "Health", "headline": {"main": "The Crisis in Long-Term Care", "kicker": "The New Old Age"}, "slideshow_credits": null, "_id": "4fd3a1a08eb7c8105d8e8674", "document_type": "blogpost"}