{"subsection_name": null, "pub_date": "2011-10-28T00:00:00Z", "byline": [], "abstract": null, "word_count": "20", "print_page": null, "news_desk": "Sports", "snippet": "The Pan American Games continued in Mexico and many of the world\u2019s best snowboarders and freestyle skiers performed in London.", "multimedia": [{"subtype": "wide", "width": 190, "legacy": {"wide": "images/2011/10/28/sports/20111028-photoreplay-slide-EOD2/20111028-photoreplay-slide-EOD2-thumbWide.jpg", "widewidth": "190", "wideheight": "126"}, "type": "image", "url": "images/2011/10/28/sports/20111028-photoreplay-slide-EOD2/20111028-photoreplay-slide-EOD2-thumbWide.jpg", "height": 126}, {"subtype": "thumbnail", "width": 75, "legacy": {"thumbnailwidth": "75", "thumbnail": "images/2011/10/28/sports/20111028-photoreplay-slide-EOD2/20111028-photoreplay-slide-EOD2-thumbStandard.jpg", "thumbnailheight": "75"}, "type": "image", "url": "images/2011/10/28/sports/20111028-photoreplay-slide-EOD2/20111028-photoreplay-slide-EOD2-thumbStandard.jpg", "height": 75}], "source": "The New York Times", "blog": [], "keywords": [{"name": "subject", "is_major": "N", "value": "Freestyle Skiing", "rank": "1"}, {"name": "subject", "is_major": "N", "value": "Diving (Sports Event)", "rank": "2"}, {"name": "subject", "is_major": "N", "value": "Speedskating", "rank": "3"}, {"name": "subject", "is_major": "N", "value": "Kayaks", "rank": "4"}, {"name": "subject", "is_major": "N", "value": "Air Shows and Air Racing", "rank": "5"}], "type_of_material": "Slideshow", "lead_paragraph": "The Pan American Games continued in Mexico and many of the world\u2019s best snowboarders and freestyle skiers performed in London.", "web_url": "http://www.nytimes.com/slideshow/2011/10/28/sports/20111028-photoreplay.html", "section_name": "Sports", "headline": {"main": "Photo Replay: Oct.28"}, "slideshow_credits": null, "_id": "513e0410cf28d04ae0001870", "document_type": "multimedia"}