{"subsection_name": null, "pub_date": "2011-10-16T00:00:00Z", "byline": [], "abstract": null, "word_count": "20", "print_page": null, "news_desk": "Style", "snippet": "A selection of Muriel Brandolini\u2019s furniture and art collection will be auctioned next week at Phillips de Pury & Company.", "multimedia": [{"subtype": "wide", "width": 190, "legacy": {"wide": "images/2011/10/16/style/20111016-BRANDOLINI-slide-GHJY/20111016-BRANDOLINI-slide-GHJY-thumbWide.jpg", "widewidth": "190", "wideheight": "126"}, "type": "image", "url": "images/2011/10/16/style/20111016-BRANDOLINI-slide-GHJY/20111016-BRANDOLINI-slide-GHJY-thumbWide.jpg", "height": 126}], "source": "The New York Times", "blog": [], "keywords": [{"name": "subject", "is_major": "N", "value": "Art", "rank": "1"}, {"name": "subject", "is_major": "N", "value": "Design", "rank": "2"}, {"name": "subject", "is_major": "N", "value": "Auctions", "rank": "3"}, {"name": "subject", "is_major": "N", "value": "Furniture", "rank": "4"}], "type_of_material": "Slideshow", "lead_paragraph": "A selection of Muriel Brandolini\u2019s furniture and art collection will be auctioned next week at Phillips de Pury & Company.", "web_url": "http://www.nytimes.com/slideshow/2011/10/16/style/20111016-BRANDOLINI.html", "section_name": "Style", "headline": {"main": "At Muriel Brandolini\u2019s Auction, a Style Maker\u2019s Cache"}, "slideshow_credits": null, "_id": "513e066ecf28d04ae0002241", "document_type": "multimedia"}