{"subsection_name": null, "pub_date": "2011-10-23T00:00:00Z", "byline": {"original": "By THE ASSOCIATED PRESS", "contributor": "", "organization": "THE ASSOCIATED PRESS", "person": []}, "abstract": "Americans Meryl Davis and Charlie White win ice dancing title at Skate America competition.", "word_count": "51", "print_page": "8", "news_desk": "Sports", "snippet": "The Americans Meryl Davis and Charlie White skated an elegant routine to win the ice dancing title at Skate America in Ontario, Calif.", "multimedia": [], "source": "The New York Times", "blog": [], "keywords": [{"name": "subject", "is_major": "Y", "value": "Ice Dancing", "rank": "1"}, {"name": "organizations", "is_major": "Y", "value": "Skate America", "rank": "2"}, {"name": "persons", "is_major": "Y", "value": "White, Charlie", "rank": "3"}, {"name": "persons", "is_major": "Y", "value": "Davis, Meryl", "rank": "4"}, {"name": "subject", "is_major": "N", "value": "Ice Skating", "rank": "5"}, {"name": "subject", "is_major": "Y", "value": "Figure Skating", "rank": "6"}], "type_of_material": "Brief", "lead_paragraph": "The Americans Meryl Davis and Charlie White skated an elegant routine to win the ice dancing title at Skate America in Ontario, Calif.", "web_url": "http://www.nytimes.com/2011/10/23/sports/United-States-Wins-Ice-Dancing-Title.html", "section_name": "Sports", "headline": {"main": "U.S. Wins Ice Dancing Title", "print_headline": "U.S. Wins Ice Dancing Title", "content_kicker": "Sports Briefing | Figure Skating"}, "slideshow_credits": null, "_id": "517e83c0cf28d041ca00033c", "document_type": "article"}