{"subsection_name": null, "pub_date": "2011-10-03T00:00:00Z", "byline": {"original": "By THE ASSOCIATED PRESS", "contributor": "", "organization": "THE ASSOCIATED PRESS", "person": []}, "abstract": null, "word_count": "183", "print_page": "19", "news_desk": "Metro", "snippet": "The newly reopened September 11th Victim Compensation Fund will start taking applications on Monday.", "multimedia": [], "source": "The New York Times", "blog": [], "keywords": [{"name": "subject", "is_major": "N", "value": "September 11 (2001)", "rank": "1"}, {"name": "organizations", "is_major": "N", "value": "September 11 Victim Compensation Fund", "rank": "2"}, {"name": "glocations", "is_major": "N", "value": "Manhattan (NYC)", "rank": "3"}], "type_of_material": "News", "lead_paragraph": "The newly reopened September 11th Victim Compensation Fund will start taking applications on Monday.", "web_url": "http://www.nytimes.com/2011/10/03/nyregion/september-11th-victim-compensation-fund-accepts-applications.html", "section_name": "N.Y. / Region", "headline": {"main": "Ground Zero Fund Opens to Applicants", "print_headline": "Ground Zero Fund Opens to Applicants", "seo": "September 11th Victim Compensation Fund Accepts Applications"}, "slideshow_credits": null, "_id": "5401ad7d38f0d841b2f39f92", "document_type": "article"}