{"subsection_name": "Economy", "pub_date": "2011-10-04T00:00:00Z", "byline": {"original": "By REUTERS", "contributor": "", "organization": "REUTERS", "person": []}, "abstract": null, "word_count": "215", "print_page": "", "news_desk": "Business", "snippet": "Manufacturing in September and construction spending in August were better than expected, two reports said on Monday.", "multimedia": [], "source": "The New York Times", "blog": [], "keywords": [{"name": "organizations", "is_major": "N", "value": "Institute for Supply Management", "rank": "1"}, {"name": "subject", "is_major": "N", "value": "Factories and Manufacturing", "rank": "2"}, {"name": "subject", "is_major": "N", "value": "United States Economy", "rank": "3"}], "type_of_material": "News", "lead_paragraph": "Manufacturing in September and construction spending in August were better than expected, two reports said on Monday.", "web_url": "http://www.nytimes.com/2011/10/04/business/economy/data-shows-some-growth-in-us-economy.html", "section_name": "Business Day", "headline": {"main": "Data Shows Some Growth in U.S. Economy", "print_headline": "Data Shows Some Growth in U.S. Economy"}, "slideshow_credits": null, "_id": "5401b18f38f0d841b2f39fe4", "document_type": "article"}