{"subsection_name": null, "pub_date": "2011-10-31T00:00:00Z", "byline": null, "abstract": null, "word_count": "462", "print_page": null, "news_desk": "Business Day", "snippet": "Audio and transcripts from an interview with Ruth Madoff recorded by The Times\u2019s Diana B. Henriques in October 2011.", "multimedia": [], "source": "The New York Times", "blog": [], "keywords": [{"name": "persons", "is_major": "N", "value": "Madoff, Bernard L", "rank": "1"}, {"name": "persons", "is_major": "N", "value": "Madoff, Ruth", "rank": "2"}, {"name": "subject", "is_major": "N", "value": "Frauds and Swindling", "rank": "3"}], "type_of_material": "Interactive Feature", "lead_paragraph": "Audio and transcripts from an interview with Ruth Madoff recorded by The Times\u2019s Diana B. Henriques in October 2011.", "web_url": "http://www.nytimes.com/interactive/2011/10/31/business/interview-ruth-madoff.html", "section_name": "Business Day", "headline": {"main": "Interview: Ruth Madoff"}, "slideshow_credits": null, "_id": "5402ab7e38f0d80cceb1fdcb", "document_type": "multimedia"}