{"subsection_name": "Environment", "pub_date": "2011-10-06T13:08:09Z", "byline": {"original": "By THE NEW YORK TIMES", "organization": "The New York Times", "person": []}, "abstract": "Although the Texas  water code exempts oil and gas drilling from some rules enacted by groundwater districts, they will apply to fracking nonetheless, some local officials decide.", "word_count": "139", "print_page": null, "news_desk": null, "snippet": "Although the Texas  water code exempts oil and gas drilling from some rules enacted by groundwater districts, they will apply to fracking nonetheless, some local officials decide.", "multimedia": [], "source": "The New York Times", "blog": [], "keywords": [], "type_of_material": "Blog", "lead_paragraph": null, "web_url": "http://green.blogs.nytimes.com/2011/10/06/on-our-radar-fracking-vs-drought/", "section_name": "Science", "headline": {"main": "On Our Radar: Fracking vs. Drought", "kicker": "Green Blog"}, "slideshow_credits": null, "_id": "54f3d2e138f0d84018917df9", "document_type": "blogpost"}