{"subsection_name": null, "pub_date": "2011-10-22T14:06:38Z", "byline": {"original": "By THE NEW YORK TIIMES", "organization": "THE MES", "person": []}, "abstract": "Here's the latest batch of readers' responses to some of the shows collected through Storify.", "word_count": "85", "print_page": null, "news_desk": null, "snippet": "Here's the latest batch of readers' responses to some of the shows collected through Storify.", "multimedia": [{"subtype": "thumbnail", "width": 75, "legacy": {"thumbnailwidth": "75", "thumbnail": "images/2011/10/23/arts/music/cmj-dum-dum/cmj-dum-dum-thumbStandard.jpg", "thumbnailheight": "75"}, "type": "image", "url": "images/2011/10/23/arts/music/cmj-dum-dum/cmj-dum-dum-thumbStandard.jpg", "height": 75}], "source": "The New York Times", "blog": [], "keywords": [], "type_of_material": "Blog", "lead_paragraph": null, "web_url": "http://artsbeat.blogs.nytimes.com/2011/10/22/cmj-day-4-twitter-reviews-of-dum-dum-girls-walk-the-moon-metronomy-and-more/", "section_name": "Arts", "headline": {"main": "CMJ: Day 4 Twitter Reviews of Dum Dum Girls, Walk the Moon, Metronomy and More", "kicker": "ArtsBeat"}, "slideshow_credits": null, "_id": "54f3b3e638f0d84018917723", "document_type": "blogpost"}