{"subsection_name": null, "pub_date": "2011-10-16T00:00:00Z", "byline": [], "abstract": null, "word_count": "42", "print_page": null, "news_desk": "Magazine", "snippet": "Approaching the Statue of Liberty by boat for the first time in 1999, Wang Qingsong had visions of Botticelli. \u201cIt was just a little bit like \u2019The Birth of Venus,\u2019\u201d he said. \u2018\u2018It was a goddess born from the water.\u2019\u2019", "multimedia": [], "source": "The New York Times", "blog": [], "keywords": [{"name": "subject", "is_major": "N", "value": "Statue of Liberty", "rank": "1"}], "type_of_material": "Interactive Feature", "lead_paragraph": "Approaching the Statue of Liberty by boat for the first time in 1999, Wang Qingsong had visions of Botticelli. \u201cIt was just a little bit like \u2019The Birth of Venus,\u2019\u201d he said. \u2018\u2018It was a goddess born from the water.\u2019\u2019", "web_url": "http://www.nytimes.com/interactive/2011/10/16/magazine/LOOKchina.html", "section_name": "Magazine", "headline": {"main": "Comrade Liberty", "seo": "Comrade Liberty", "kicker": "Look"}, "slideshow_credits": null, "_id": "551c662a38f0d87335c1a24f", "document_type": "multimedia"}