{"subsection_name": "Politics", "pub_date": "2016-08-15T08:04:55Z", "byline": {"original": "By THE ASSOCIATED PRESS", "organization": "THE ASSOCIATED PRESS", "person": []}, "abstract": null, "word_count": "812", "print_page": null, "news_desk": "None", "snippet": "In a story Aug. 15 about efforts to create more national monuments, The Associated Press reported erroneously that President Barack Obama has created or expanded the most national monuments of any president. Obama has protected more land and water...", "multimedia": [], "source": "", "blog": [], "keywords": [], "type_of_material": "News", "lead_paragraph": "In a story Aug. 15 about efforts to create more national monuments, The Associated Press reported erroneously that President Barack Obama has created or expanded the most national monuments of any president. Obama has protected more land and water using national monument designations than any other president. But in total number of monuments, he falls short of President Franklin Roosevelt.", "web_url": "http://www.nytimes.com/aponline/2016/08/15/us/politics/ap-us-obama-national-monuments.html", "section_name": "U.S.", "headline": {"main": "Correction: Obama-National Monuments Story", "print_headline": "Correction: Obama-National Monuments Story"}, "slideshow_credits": null, "_id": "57b1781a95d0e021d7980b7f", "document_type": "article"}